python_main/__init__.py
python_main/py.typed
python_main-2.0.0.dist-info/METADATA
python_main-2.0.0.dist-info/WHEEL
python_main-2.0.0.dist-info/RECORD
