Metadata-Version: 2.1
Name: python-main
Version: 2.0.0
Summary: Decorator which runs the tagged function if the current module is being run as a script. No more `if __name__ == "__main__"` madness.
Home-page: https://github.com/flipbit03/main
License: BSD
Author: Cadu
Author-email: cadu.coelho@gmail.com
Requires-Python: >=3.9,<4.0
Classifier: Development Status :: 5 - Production/Stable
Classifier: Intended Audience :: Developers
Classifier: License :: OSI Approved :: BSD License
Classifier: License :: Other/Proprietary License
Classifier: Natural Language :: English
Classifier: Programming Language :: Python :: 3
Classifier: Programming Language :: Python :: 3.9
Classifier: Programming Language :: Python :: 3.10
Classifier: Programming Language :: Python :: 3.11
Classifier: Programming Language :: Python :: 3.12
Classifier: Programming Language :: Python :: 3.13
